polygraphy/__init__.py
polygraphy/config.py
polygraphy/constants.py
polygraphy/backend/__init__.py
polygraphy/backend/base/__init__.py
polygraphy/backend/base/loader.py
polygraphy/backend/base/runner.py
polygraphy/backend/base/util.py
polygraphy/backend/common/__init__.py
polygraphy/backend/common/loader.py
polygraphy/backend/onnx/__init__.py
polygraphy/backend/onnx/loader.py
polygraphy/backend/onnx/util.py
polygraphy/backend/onnxrt/__init__.py
polygraphy/backend/onnxrt/loader.py
polygraphy/backend/onnxrt/runner.py
polygraphy/backend/pluginref/__init__.py
polygraphy/backend/pluginref/references.py
polygraphy/backend/pluginref/runner.py
polygraphy/backend/pyt/__init__.py
polygraphy/backend/pyt/runner.py
polygraphy/backend/tensorrt_rtx/__init__.py
polygraphy/backend/tensorrt_rtx/config.py
polygraphy/backend/tf/__init__.py
polygraphy/backend/tf/loader.py
polygraphy/backend/tf/runner.py
polygraphy/backend/tf/util.py
polygraphy/backend/trt/__init__.py
polygraphy/backend/trt/algorithm_selector.py
polygraphy/backend/trt/calibrator.py
polygraphy/backend/trt/config.py
polygraphy/backend/trt/file_reader.py
polygraphy/backend/trt/loader.py
polygraphy/backend/trt/profile.py
polygraphy/backend/trt/runner.py
polygraphy/backend/trt/util.py
polygraphy/common/__init__.py
polygraphy/common/interface.py
polygraphy/common/struct.py
polygraphy/comparator/__init__.py
polygraphy/comparator/comparator.py
polygraphy/comparator/compare.py
polygraphy/comparator/data_loader.py
polygraphy/comparator/postprocess.py
polygraphy/comparator/struct.py
polygraphy/comparator/util.py
polygraphy/cuda/__init__.py
polygraphy/cuda/cuda.py
polygraphy/datatype/__init__.py
polygraphy/datatype/datatype.py
polygraphy/datatype/numpy.py
polygraphy/datatype/onnx.py
polygraphy/datatype/onnxrt.py
polygraphy/datatype/tensorrt.py
polygraphy/datatype/torch.py
polygraphy/exception/__init__.py
polygraphy/exception/exception.py
polygraphy/func/__init__.py
polygraphy/func/func.py
polygraphy/json/__init__.py
polygraphy-0.49.26.dist-info/LICENSE.txt
polygraphy-0.49.26.dist-info/METADATA
polygraphy-0.49.26.dist-info/WHEEL
polygraphy-0.49.26.dist-info/entry_points.txt
polygraphy-0.49.26.dist-info/top_level.txt
polygraphy-0.49.26.dist-info/zip-safe
polygraphy-0.49.26.dist-info/RECORD
