Metadata-Version: 2.1
Name: polygraphy
Version: 0.49.26
Summary: Polygraphy: A Deep Learning Inference Prototyping and Debugging Toolkit
Home-page: https://github.com/NVIDIA/TensorRT/tree/main/tools/Polygraphy
Author: NVIDIA
Author-email: svc_tensorrt@nvidia.com
License: Apache 2.0
Classifier: Intended Audience :: Developers
Classifier: Programming Language :: Python :: 3
Requires-Python: >=3.6
License-File: LICENSE.txt
